pymultirole_plugins/__init__.py
pymultirole_plugins/schema.py
pymultirole_plugins/util.py
pymultirole_plugins/v1/__init__.py
pymultirole_plugins/v1/annotator.py
pymultirole_plugins/v1/converter.py
pymultirole_plugins/v1/formatter.py
pymultirole_plugins/v1/processor.py
pymultirole_plugins/v1/schema.py
pymultirole_plugins/v1/segmenter.py
pymultirole_plugins-0.5.671.dist-info/WHEEL
pymultirole_plugins-0.5.671.dist-info/METADATA
pymultirole_plugins-0.5.671.dist-info/RECORD
